{
  "project_info": {
    "project_number": "1047123368889",
    "firebase_url": "https://scriptclickblue-8e8be-default-rtdb.firebaseio.com",
    "project_id": "scriptclickblue-8e8be",
    "storage_bucket": "scriptclickblue-8e8be.appspot.com"
  },
  "client": [
    {
      "client_info": {
        "mobilesdk_app_id": "1:1047123368889:android:6e1fb19e8ada5a1df37468",
        "android_client_info": {
          "package_name": "com.example.mainscreen"
        }
      },
      "oauth_client": [
        {
          "client_id": "1047123368889-ug1ot4er283itt0iqcn0gs0uds5fl8vm.apps.googleusercontent.com",
          "client_type": 3
        }
      ],
      "api_key": [
        {
          "current_key": "AIzaSyDS4x8SCg_l_2hE3RnivDpTYmxCLtYhbcM"
        }
      ],
      "services": {
        "appinvite_service": {
          "other_platform_oauth_client": [
            {
              "client_id": "1047123368889-ug1ot4er283itt0iqcn0gs0uds5fl8vm.apps.googleusercontent.com",
              "client_type": 3
            }
          ]
        }
      }
    },
    {
      "client_info": {
        "mobilesdk_app_id": "1:1047123368889:android:a5ee3189063b5883f37468",
        "android_client_info": {
          "package_name": "com.example.testapp"
        }
      },
      "oauth_client": [
        {
          "client_id": "1047123368889-ug1ot4er283itt0iqcn0gs0uds5fl8vm.apps.googleusercontent.com",
          "client_type": 3
        }
      ],
      "api_key": [
        {
          "current_key": "AIzaSyDS4x8SCg_l_2hE3RnivDpTYmxCLtYhbcM"
        }
      ],
      "services": {
        "appinvite_service": {
          "other_platform_oauth_client": [
            {
              "client_id": "1047123368889-ug1ot4er283itt0iqcn0gs0uds5fl8vm.apps.googleusercontent.com",
              "client_type": 3
            }
          ]
        }
      }
    }
  ],
  "configuration_version": "1"
}